parse_qwantz/__init__.py
parse_qwantz/__main__.py
parse_qwantz/box.py
parse_qwantz/char_variants.py
parse_qwantz/cli.py
parse_qwantz/color_logs.py
parse_qwantz/colors.py
parse_qwantz/detect_thought.py
parse_qwantz/elements.py
parse_qwantz/fonts.py
parse_qwantz/hyphens.py
parse_qwantz/image_viewer.py
parse_qwantz/lines.py
parse_qwantz/main.py
parse_qwantz/match_blocks.py
parse_qwantz/match_lines.py
parse_qwantz/match_thought.py
parse_qwantz/panel_overrides.py
parse_qwantz/panels.py
parse_qwantz/parser.py
parse_qwantz/pixels.py
parse_qwantz/prepare_image.py
parse_qwantz/shape.py
parse_qwantz/simple_image.py
parse_qwantz/svg_gen.py
parse_qwantz/text_blocks.py
parse_qwantz/text_lines.py
parse_qwantz/data/panel_overrides.json
parse_qwantz/dict/html-words.txt
parse_qwantz/dict/manual-additions.txt
parse_qwantz/dict/manual-removed.txt
parse_qwantz/dict/unambiguous-qwantz.txt
parse_qwantz/img/ask-professor-science.svg
parse_qwantz/img/batman-left.svg
parse_qwantz/img/batman-right.svg
parse_qwantz/img/blank.svg
parse_qwantz/img/italic13.png
parse_qwantz/img/mask.png
parse_qwantz/img/regular10.png
parse_qwantz/img/regular11.png
parse_qwantz/img/regular12.png
parse_qwantz/img/regular13.png
parse_qwantz/img/regular8.png
parse_qwantz/img/regular9.png
parse_qwantz/img/serif13.png
parse_qwantz-2025.11.0.dist-info/licenses/LICENSE
parse_qwantz-2025.11.0.dist-info/METADATA
parse_qwantz-2025.11.0.dist-info/WHEEL
parse_qwantz-2025.11.0.dist-info/entry_points.txt
parse_qwantz-2025.11.0.dist-info/top_level.txt
parse_qwantz-2025.11.0.dist-info/RECORD
