Metadata-Version: 2.4
Name: parse_qwantz
Version: 2025.11.0
Summary: Transcript generator for Dinosaur Comics
Author-email: Jan Szejko <jan.szejko@gmail.com>
Project-URL: homepage, https://github.com/janek37/parse_qwantz
Classifier: Development Status :: 3 - Alpha
Classifier: Programming Language :: Python :: 3.10
Classifier: Environment :: Console
Classifier: Intended Audience :: End Users/Desktop
Classifier: License :: OSI Approved :: MIT License
Classifier: Natural Language :: English
Classifier: Operating System :: OS Independent
Classifier: Topic :: Multimedia :: Graphics :: Graphics Conversion
Classifier: Topic :: Scientific/Engineering :: Image Recognition
Classifier: Typing :: Typed
Requires-Python: >=3.10
License-File: LICENSE
Requires-Dist: Pillow
Requires-Dist: typer
Provides-Extra: dev
Requires-Dist: pytest; extra == "dev"
Dynamic: license-file
